kubesae/__init__.py
kubesae/image.py
kubesae/info.py
kubesae/pod.py
kubesae/utils.py
kubesae/ansible/__init__.py
kubesae/ansible/deploy.py
kubesae/ansible/vars.py
kubesae/providers/__init__.py
kubesae/providers/aws.py
kubesae/providers/gcp.py
invoke_kubesae-0.1.0.dist-info/LICENSE
invoke_kubesae-0.1.0.dist-info/METADATA
invoke_kubesae-0.1.0.dist-info/WHEEL
invoke_kubesae-0.1.0.dist-info/top_level.txt
invoke_kubesae-0.1.0.dist-info/RECORD
