Metadata-Version: 2.1
Name: invoke-kubesae
Version: 0.1.0
Summary: An invoke tasks library to manage a kubernetes project.
Home-page: https://github.com/caktus/invoke-kubesae
Author: Caktus Group
Author-email: solutions@caktusgroup.com
License: BSD
Classifier: Development Status :: 5 - Production/Stable
Classifier: Intended Audience :: Developers
Classifier: License :: OSI Approved :: BSD License
Classifier: Operating System :: OS Independent
Classifier: Programming Language :: Python :: 3
Classifier: Topic :: Software Development :: Build Tools
Requires-Python: >=3.5
License-File: LICENSE
Requires-Dist: boto3 (>=1.16)
Requires-Dist: invoke (>=1.4)
Requires-Dist: colorama (>=0.4)
Requires-Dist: ansible (>=2.9)
